gy_multiprocessing
