Metadata-Version: 2.1
Name: gy-multiprocessing
Version: 0.2.1
Summary: Run function in multiple processes
Home-page: https://github.com/guangyu-he/gy-multiprocessing
Author: Guangyu He
Author-email: me@heguangyu.net
License: UNKNOWN
Platform: UNKNOWN
Classifier: Development Status :: 4 - Beta
Classifier: Programming Language :: Python :: 3
Classifier: Operating System :: OS Independent
Requires-Python: >=3.7
